odoo/addons/web_ir_actions_act_multi/README.rst
odoo/addons/web_ir_actions_act_multi/__init__.py
odoo/addons/web_ir_actions_act_multi/__manifest__.py
odoo/addons/web_ir_actions_act_multi/i18n/es.po
odoo/addons/web_ir_actions_act_multi/i18n/it.po
odoo/addons/web_ir_actions_act_multi/i18n/web_ir_actions_act_multi.pot
odoo/addons/web_ir_actions_act_multi/i18n/zh_CN.po
odoo/addons/web_ir_actions_act_multi/models/__init__.py
odoo/addons/web_ir_actions_act_multi/models/ir_actions.py
odoo/addons/web_ir_actions_act_multi/models/ir_model.py
odoo/addons/web_ir_actions_act_multi/readme/CONTRIBUTORS.md
odoo/addons/web_ir_actions_act_multi/readme/DESCRIPTION.md
odoo/addons/web_ir_actions_act_multi/readme/USAGE.md
odoo/addons/web_ir_actions_act_multi/security/ir.model.access.csv
odoo/addons/web_ir_actions_act_multi/static/description/icon.png
odoo/addons/web_ir_actions_act_multi/static/description/index.html
odoo/addons/web_ir_actions_act_multi/static/src/js/web_ir_actions_act_multi.esm.js
odoo_addon_web_ir_actions_act_multi-18.0.1.0.0.2.dist-info/METADATA
odoo_addon_web_ir_actions_act_multi-18.0.1.0.0.2.dist-info/WHEEL
odoo_addon_web_ir_actions_act_multi-18.0.1.0.0.2.dist-info/top_level.txt
odoo_addon_web_ir_actions_act_multi-18.0.1.0.0.2.dist-info/RECORD
